custom_context_menu-0.0.1.dist-info/licenses/LICENSE
radio_button/__init__.py
radio_button/example.py
radio_button/frontend/build/bootstrap.min.css
radio_button/frontend/build/index.html
radio_button/frontend/build/assets/index-BleM5BcU.js
custom_context_menu-0.0.1.dist-info/METADATA
custom_context_menu-0.0.1.dist-info/WHEEL
custom_context_menu-0.0.1.dist-info/top_level.txt
custom_context_menu-0.0.1.dist-info/RECORD
